qa_trainer/__init__.py
qa_trainer/trainer.py
qa_trainer-0.1.dist-info/METADATA
qa_trainer-0.1.dist-info/WHEEL
qa_trainer-0.1.dist-info/top_level.txt
qa_trainer-0.1.dist-info/RECORD
