Metadata-Version: 2.4
Name: qa_trainer
Version: 0.1
Summary: Train QA models from feedback with Optuna hyperparameter tuning
Author: Your Name
Requires-Dist: simpletransformers>=0.64.3
Requires-Dist: optuna
Requires-Dist: torch
Requires-Dist: transformers
Dynamic: author
Dynamic: description
Dynamic: description-content-type
Dynamic: requires-dist
Dynamic: summary
